tap_hubplanner/__init__.py
tap_hubplanner/client.py
tap_hubplanner/discover.py
tap_hubplanner/schema.py
tap_hubplanner/sync.py
tap_hubplanner/schemas/billingrate.json
tap_hubplanner/schemas/bookings.json
tap_hubplanner/schemas/clients.json
tap_hubplanner/schemas/events.json
tap_hubplanner/schemas/holiday.json
tap_hubplanner/schemas/project-tag.json
tap_hubplanner/schemas/project.json
tap_hubplanner/schemas/projectgroup.json
tap_hubplanner/schemas/resource-tag.json
tap_hubplanner/schemas/resource.json
tap_hubplanner/schemas/resourcegroup.json
tap_hubplanner/schemas/unassigned-work.json
tap_hubplanner-0.1.2.dist-info/LICENSE
tap_hubplanner-0.1.2.dist-info/METADATA
tap_hubplanner-0.1.2.dist-info/WHEEL
tap_hubplanner-0.1.2.dist-info/entry_points.txt
tap_hubplanner-0.1.2.dist-info/top_level.txt
tap_hubplanner-0.1.2.dist-info/RECORD
