Metadata-Version: 2.1
Name: tap-hubplanner
Version: 0.1.2
Summary: Singer.io tap for extracting data from the Hub Planner REST API
Home-page: https://github.com/rangle/tap-hubplanner
Author: Rangle.io
License: UNKNOWN
Platform: UNKNOWN
Classifier: Programming Language :: Python :: 3 :: Only
Requires-Dist: singer-python (==5.5.0)
Requires-Dist: requests (==2.21.0)
Requires-Dist: backoff (==1.3.2)
Requires-Dist: ratelimit (==2.2.1)
Provides-Extra: dev
Requires-Dist: pylint ; extra == 'dev'
Requires-Dist: autopep8 ; extra == 'dev'
Requires-Dist: rope ; extra == 'dev'
